{
  "settlementAsset": "",
  "quoteName": "",
  "oracleSpecForSettlementPrice": {
    "id": "1",
    "createdAt": "0",
    "updatedAt": "0",
    "pubKeys": [
      "0xDEADBEEF",
      "0xCAFEDOOD"
    ],
    "filters": [
      {
        "key": {
          "name": "prices.ETH.value",
          "type": "TYPE_INTEGER"
        },
        "conditions": [
        ]
      }
    ],
    "status": "STATUS_UNSPECIFIED"
  },
  "oracleSpecForTradingTermination": {
    "id": "2",
    "createdAt": "0",
    "updatedAt": "0",
    "pubKeys": [
      "0xDEADBEEF",
      "0xCAFEDOOD"
    ],
    "filters": [
      {
        "key": {
          "name": "trading.terminated",
          "type": "TYPE_BOOLEAN"
        },
        "conditions": [
        ]
      }
    ],
    "status": "STATUS_UNSPECIFIED"
  },
  "oracleSpecBinding": {
    "settlementPriceProperty": "prices.ETH.value",
    "tradingTerminationProperty": "trading.terminated"
  }
}
