{
  "swagger": "2.0",
  "info": {
    "title": "api/grpc.proto",
    "version": "version not set"
  },
  "schemes": [
    "http",
    "https"
  ],
  "consumes": [
    "application/json"
  ],
  "produces": [
    "application/json"
  ],
  "paths": {
    "/1.0/candles": {
      "get": {
        "operationId": "TradeCandles",
        "responses": {
          "200": {
            "description": "",
            "schema": {
              "$ref": "#/definitions/grpcTradeCandlesResponse"
            }
          }
        },
        "parameters": [
          {
            "name": "market",
            "in": "query",
            "required": false,
            "type": "string"
          },
          {
            "name": "since",
            "in": "query",
            "required": false,
            "type": "string"
          },
          {
            "name": "interval",
            "in": "query",
            "required": false,
            "type": "string",
            "format": "uint64"
          }
        ],
        "tags": [
          "trading"
        ]
      }
    },
    "/1.0/createOrder": {
      "post": {
        "operationId": "CreateOrder",
        "responses": {
          "200": {
            "description": "",
            "schema": {
              "$ref": "#/definitions/grpcOrderResponse"
            }
          }
        },
        "parameters": [
          {
            "name": "body",
            "in": "body",
            "required": true,
            "schema": {
              "$ref": "#/definitions/vegaOrder"
            }
          }
        ],
        "tags": [
          "trading"
        ]
      }
    },
    "/1.0/marketOrder": {
      "get": {
        "operationId": "OrderByMarketAndId",
        "responses": {
          "200": {
            "description": "",
            "schema": {
              "$ref": "#/definitions/grpcOrderByMarketAndIdResponse"
            }
          }
        },
        "parameters": [
          {
            "name": "market",
            "in": "query",
            "required": false,
            "type": "string"
          },
          {
            "name": "id",
            "in": "query",
            "required": false,
            "type": "string"
          }
        ],
        "tags": [
          "trading"
        ]
      }
    },
    "/1.0/marketOrders": {
      "get": {
        "operationId": "OrdersByMarket",
        "responses": {
          "200": {
            "description": "",
            "schema": {
              "$ref": "#/definitions/grpcOrdersByMarketResponse"
            }
          }
        },
        "parameters": [
          {
            "name": "market",
            "in": "query",
            "required": false,
            "type": "string"
          },
          {
            "name": "params.limit",
            "in": "query",
            "required": false,
            "type": "string",
            "format": "uint64"
          }
        ],
        "tags": [
          "trading"
        ]
      }
    },
    "/1.0/marketTrades": {
      "get": {
        "operationId": "TradesByMarket",
        "responses": {
          "200": {
            "description": "",
            "schema": {
              "$ref": "#/definitions/grpcTradesByMarketResponse"
            }
          }
        },
        "parameters": [
          {
            "name": "market",
            "in": "query",
            "required": false,
            "type": "string"
          },
          {
            "name": "params.limit",
            "in": "query",
            "required": false,
            "type": "string",
            "format": "uint64"
          }
        ],
        "tags": [
          "trading"
        ]
      }
    },
    "/1.0/markets": {
      "get": {
        "operationId": "Markets",
        "responses": {
          "200": {
            "description": "",
            "schema": {
              "$ref": "#/definitions/grpcMarketsResponse"
            }
          }
        },
        "tags": [
          "trading"
        ]
      }
    },
    "/1.0/orderBookDepth": {
      "get": {
        "operationId": "OrderBookDepth",
        "responses": {
          "200": {
            "description": "",
            "schema": {
              "$ref": "#/definitions/grpcOrderBookDepthResponse"
            }
          }
        },
        "parameters": [
          {
            "name": "market",
            "in": "query",
            "required": false,
            "type": "string"
          }
        ],
        "tags": [
          "trading"
        ]
      }
    },
    "/1.0/partyOrders": {
      "get": {
        "operationId": "OrdersByParty",
        "responses": {
          "200": {
            "description": "",
            "schema": {
              "$ref": "#/definitions/grpcOrdersByPartyResponse"
            }
          }
        },
        "parameters": [
          {
            "name": "party",
            "in": "query",
            "required": false,
            "type": "string"
          },
          {
            "name": "params.limit",
            "in": "query",
            "required": false,
            "type": "string",
            "format": "uint64"
          }
        ],
        "tags": [
          "trading"
        ]
      }
    },
    "/1.0/partyPositions": {
      "get": {
        "summary": "rpc TradesForOrder(TradesForOrderRequest) return (TradesForOrderResponse);        TODO",
        "operationId": "PositionsByParty",
        "responses": {
          "200": {
            "description": "",
            "schema": {
              "$ref": "#/definitions/grpcPositionsByPartyResponse"
            }
          }
        },
        "parameters": [
          {
            "name": "party",
            "in": "query",
            "required": false,
            "type": "string"
          }
        ],
        "tags": [
          "trading"
        ]
      }
    }
  },
  "definitions": {
    "OrderType": {
      "type": "string",
      "enum": [
        "GTC",
        "GTT",
        "ENE",
        "FOK"
      ],
      "default": "GTC"
    },
    "grpcMarketsResponse": {
      "type": "object",
      "properties": {
        "markets": {
          "type": "array",
          "items": {
            "type": "string"
          }
        }
      }
    },
    "grpcOptionalParams": {
      "type": "object",
      "properties": {
        "limit": {
          "type": "string",
          "format": "uint64"
        }
      }
    },
    "grpcOrderBookDepthResponse": {
      "type": "object",
      "properties": {
        "name": {
          "type": "string"
        },
        "buy": {
          "type": "array",
          "items": {
            "$ref": "#/definitions/vegaPriceLevel"
          }
        },
        "sell": {
          "type": "array",
          "items": {
            "$ref": "#/definitions/vegaPriceLevel"
          }
        }
      }
    },
    "grpcOrderByMarketAndIdResponse": {
      "type": "object",
      "properties": {
        "order": {
          "$ref": "#/definitions/vegaOrder"
        }
      }
    },
    "grpcOrderResponse": {
      "type": "object",
      "properties": {
        "success": {
          "type": "boolean",
          "format": "boolean"
        }
      }
    },
    "grpcOrdersByMarketResponse": {
      "type": "object",
      "properties": {
        "orders": {
          "type": "array",
          "items": {
            "$ref": "#/definitions/vegaOrder"
          }
        }
      }
    },
    "grpcOrdersByPartyResponse": {
      "type": "object",
      "properties": {
        "orders": {
          "type": "array",
          "items": {
            "$ref": "#/definitions/vegaOrder"
          }
        }
      }
    },
    "grpcPositionsByPartyResponse": {
      "type": "object",
      "properties": {
        "positions": {
          "type": "array",
          "items": {
            "$ref": "#/definitions/vegaMarketPosition"
          }
        }
      }
    },
    "grpcTradeCandlesResponse": {
      "type": "object",
      "properties": {
        "candles": {
          "type": "array",
          "items": {
            "$ref": "#/definitions/vegaCandle"
          }
        }
      }
    },
    "grpcTradesByMarketResponse": {
      "type": "object",
      "properties": {
        "trades": {
          "type": "array",
          "items": {
            "$ref": "#/definitions/vegaTrade"
          }
        }
      }
    },
    "vegaCandle": {
      "type": "object",
      "properties": {
        "date": {
          "type": "string"
        },
        "high": {
          "type": "string",
          "format": "uint64"
        },
        "low": {
          "type": "string",
          "format": "uint64"
        },
        "open": {
          "type": "string",
          "format": "uint64"
        },
        "close": {
          "type": "string",
          "format": "uint64"
        },
        "volume": {
          "type": "string",
          "format": "uint64"
        },
        "openBlockNumber": {
          "type": "string",
          "format": "uint64"
        },
        "closeBlockNumber": {
          "type": "string",
          "format": "uint64"
        }
      }
    },
    "vegaMarketPosition": {
      "type": "object",
      "properties": {
        "Market": {
          "type": "string"
        },
        "RealisedVolume": {
          "type": "string",
          "format": "int64"
        },
        "RealisedPNL": {
          "type": "string",
          "format": "int64"
        },
        "UnrealisedVolume": {
          "type": "string",
          "format": "int64"
        },
        "UnrealisedPNL": {
          "type": "string",
          "format": "int64"
        }
      }
    },
    "vegaOrder": {
      "type": "object",
      "properties": {
        "id": {
          "type": "string"
        },
        "market": {
          "type": "string"
        },
        "party": {
          "type": "string"
        },
        "side": {
          "$ref": "#/definitions/vegaSide"
        },
        "price": {
          "type": "string",
          "format": "uint64"
        },
        "size": {
          "type": "string",
          "format": "uint64"
        },
        "remaining": {
          "type": "string",
          "format": "uint64"
        },
        "type": {
          "$ref": "#/definitions/OrderType"
        },
        "timestamp": {
          "type": "string",
          "format": "uint64"
        }
      }
    },
    "vegaPriceLevel": {
      "type": "object",
      "properties": {
        "price": {
          "type": "string",
          "format": "uint64"
        },
        "numberOfOrders": {
          "type": "string",
          "format": "uint64"
        },
        "volume": {
          "type": "string",
          "format": "uint64"
        },
        "cumulativeVolume": {
          "type": "string",
          "format": "uint64"
        }
      }
    },
    "vegaSide": {
      "type": "string",
      "enum": [
        "Buy",
        "Sell"
      ],
      "default": "Buy"
    },
    "vegaTrade": {
      "type": "object",
      "properties": {
        "id": {
          "type": "string"
        },
        "market": {
          "type": "string"
        },
        "price": {
          "type": "string",
          "format": "uint64"
        },
        "size": {
          "type": "string",
          "format": "uint64"
        },
        "buyer": {
          "type": "string"
        },
        "seller": {
          "type": "string"
        },
        "aggressor": {
          "$ref": "#/definitions/vegaSide"
        },
        "timestamp": {
          "type": "string",
          "format": "uint64"
        }
      }
    }
  }
}
