{
  "swagger": "2.0",
  "info": {
    "title": "api/grpc.proto",
    "version": "version not set"
  },
  "schemes": [
    "http",
    "https"
  ],
  "consumes": [
    "application/json"
  ],
  "produces": [
    "application/json"
  ],
  "paths": {
    "/1.0/orders": {
      "post": {
        "operationId": "CreateOrder",
        "responses": {
          "200": {
            "description": "",
            "schema": {
              "$ref": "#/definitions/grpcOrderResponse"
            }
          }
        },
        "parameters": [
          {
            "name": "body",
            "in": "body",
            "required": true,
            "schema": {
              "$ref": "#/definitions/vegaOrder"
            }
          }
        ],
        "tags": [
          "trading"
        ]
      }
    }
  },
  "definitions": {
    "OrderType": {
      "type": "string",
      "enum": [
        "GTC",
        "GTT",
        "ENE",
        "FOK"
      ],
      "default": "GTC"
    },
    "grpcOrderResponse": {
      "type": "object",
      "properties": {
        "success": {
          "type": "boolean",
          "format": "boolean"
        }
      }
    },
    "vegaOrder": {
      "type": "object",
      "properties": {
        "id": {
          "type": "string"
        },
        "market": {
          "type": "string"
        },
        "party": {
          "type": "string"
        },
        "side": {
          "$ref": "#/definitions/vegaSide"
        },
        "price": {
          "type": "string",
          "format": "uint64"
        },
        "size": {
          "type": "string",
          "format": "uint64"
        },
        "remaining": {
          "type": "string",
          "format": "uint64"
        },
        "type": {
          "$ref": "#/definitions/OrderType"
        },
        "timestamp": {
          "type": "string",
          "format": "uint64"
        }
      }
    },
    "vegaSide": {
      "type": "string",
      "enum": [
        "Buy",
        "Sell"
      ],
      "default": "Buy"
    }
  }
}
